spotify_to_musi/__init__.py
spotify_to_musi/__main__.py
spotify_to_musi/commons.py
spotify_to_musi/exceptions.py
spotify_to_musi/main.py
spotify_to_musi/musi.py
spotify_to_musi/oauth.py
spotify_to_musi/paths.py
spotify_to_musi/py.typed
spotify_to_musi/spotify.py
spotify_to_musi/tracks_cache.py
spotify_to_musi/typings/__init__.py
spotify_to_musi/typings/core.py
spotify_to_musi/typings/musi.py
spotify_to_musi/typings/spotify.py
spotify_to_musi/typings/youtube.py
spotify_to_musi/youtube.py
spotify_to_musi/ytmusic.py
spotify_to_musi-2.0.1.dist-info/entry_points.txt
spotify_to_musi-2.0.1.dist-info/LICENSE
spotify_to_musi-2.0.1.dist-info/METADATA
spotify_to_musi-2.0.1.dist-info/WHEEL
spotify_to_musi-2.0.1.dist-info/RECORD
