Metadata-Version: 2.1
Name: spotify-to-musi
Version: 2.0.1
Summary: Transfer Spotify playlists to Musi.
Home-page: https://github.com/hexiro/spotify-to-musi
License: MIT
Keywords: spotify,music,musi,transfer,cli
Author: Hexiro
Author-email: mail@hexiro.me
Requires-Python: >=3.9,<4.0
Classifier: Environment :: Console
Classifier: License :: OSI Approved :: GNU General Public License v3 (GPLv3)
Classifier: License :: OSI Approved :: MIT License
Classifier: Natural Language :: English
Classifier: Programming Language :: Python
Classifier: Programming Language :: Python :: 3
Classifier: Programming Language :: Python :: 3.9
Classifier: Programming Language :: Python :: 3.10
Classifier: Programming Language :: Python :: 3.11
Classifier: Programming Language :: Python :: 3 :: Only
Classifier: Programming Language :: Python :: Implementation :: CPython
Classifier: Topic :: Software Development
Classifier: Topic :: Software Development :: Libraries 
Classifier: Topic :: Software Development :: Libraries :: Python Modules
Requires-Dist: aiofiles (>=23.1.0,<24.0.0)
Requires-Dist: async-cache (>=1.1.1,<2.0.0)
Requires-Dist: httpx (>=0.23.0,<=0.25.0)
Requires-Dist: pydantic (>=2.0.2,<3.0.0)
Requires-Dist: pyfy (>=2.2.0,<3.0.0)
Requires-Dist: rich (>=12.6.0,<15.0.0)
Requires-Dist: rich-click (>=1.6.1,<2.0.0)
Requires-Dist: sanic (>=23.3.0,<24.0.0)
Requires-Dist: typing-extensions (>=4.7.1,<5.0.0) ; python_version < "3.11"
Requires-Dist: uvloop (>=0.17.0,<0.18.0) ; sys_platform == "linux"
Project-URL: Bug Tracker, https://github.com/hexiro/spotify-to-musi/issues
Project-URL: Repository, https://github.com/hexiro/spotify-to-musi
